mrkup/__init__.py
mrkup/mrkup.py
mrkup-0.2.dist-info/LICENSE.md
mrkup-0.2.dist-info/METADATA
mrkup-0.2.dist-info/WHEEL
mrkup-0.2.dist-info/top_level.txt
mrkup-0.2.dist-info/RECORD
