Metadata-Version: 2.1
Name: mrkup
Version: 0.2
Summary: Compose HTML (and some XML) using Python
Home-page: https://github.com/ju-sh/mrkup/
Author: Julin S
Author-email: 
License: UNKNOWN
Project-URL: Changelog, https://github.com/ju-sh/mrkup/blob/master/CHANGELOG.md
Project-URL: Issue Tracker, https://github.com/ju-sh/mrkup/issues
Platform: UNKNOWN
Classifier: Programming Language :: Python :: 3
Classifier: License :: OSI Approved :: MIT License
Classifier: Operating System :: OS Independent
Classifier: Topic :: Text Processing :: Markup :: HTML
Classifier: Development Status :: 2 - Pre-Alpha
Classifier: Natural Language :: English
Requires-Python: >=3.6
